npgcs/__init__.py
npgcs/connectors/__init__.py
npgcs/connectors/mssql.py
npgcs/connectors/mysql.py
npgcs/connectors/postgres.py
npgcs/core/__init__.py
npgcs/core/tools.py
npgcs-1.1.1.dist-info/LICENSE
npgcs-1.1.1.dist-info/METADATA
npgcs-1.1.1.dist-info/WHEEL
npgcs-1.1.1.dist-info/top_level.txt
npgcs-1.1.1.dist-info/RECORD
