Metadata-Version: 2.1
Name: npgcs
Version: 1.1.1
Summary: A package designed for helping everyone in the team to work with data ingestion
Home-page: https://github.com/noppGithub/npgcs
Author: Nopporn Phantawee
Author-email: n.phantawee@gmail.com
License: MIT
Classifier: Development Status :: 3 - Alpha
Classifier: Intended Audience :: Developers
Classifier: License :: OSI Approved :: MIT License
Classifier: Operating System :: OS Independent
Classifier: Programming Language :: Python :: 3
Classifier: Programming Language :: Python :: 3.6
Classifier: Programming Language :: Python :: 3.7
Classifier: Programming Language :: Python :: 3.8
Classifier: Programming Language :: Python :: 3.9
Classifier: Programming Language :: Python :: 3.10
Classifier: Programming Language :: Python :: 3 :: Only
Requires-Python: >=3.6, <4
License-File: LICENSE
Requires-Dist: google-cloud-logging
Requires-Dist: google-cloud-storage
Requires-Dist: pandas
Requires-Dist: openpyxl
Provides-Extra: dev
Requires-Dist: check-manifest ; extra == 'dev'
Provides-Extra: test
Requires-Dist: coverage ; extra == 'test'
